lkmlfmt/__init__.py
lkmlfmt/__main__.py
lkmlfmt/command.py
lkmlfmt/exception.py
lkmlfmt/formatter.py
lkmlfmt/lkml.lark
lkmlfmt/logger.py
lkmlfmt/parser.py
lkmlfmt/py.typed
lkmlfmt/template.py
lkmlfmt-0.0.15.dist-info/LICENSE
lkmlfmt-0.0.15.dist-info/METADATA
lkmlfmt-0.0.15.dist-info/WHEEL
lkmlfmt-0.0.15.dist-info/entry_points.txt
lkmlfmt-0.0.15.dist-info/RECORD
