Metadata-Version: 2.1
Name: lkmlfmt
Version: 0.0.15
Summary: 
Author: kitta65
Author-email: kitta65kitta@gmail.com
Requires-Python: >=3.11,<4.0
Classifier: Programming Language :: Python :: 3
Classifier: Programming Language :: Python :: 3.11
Classifier: Programming Language :: Python :: 3.12
Classifier: Programming Language :: Python :: 3.13
Requires-Dist: click (>=8.1.3,<9.0.0)
Requires-Dist: lark (>=1.1.5,<2.0.0)
Requires-Dist: shandy-sqlfmt (>=0.20,<0.25)
